Metadata-Version: 2.1
Name: ishanki-probability-distributions
Version: 1.2
Summary: Gaussian and Binomial distributions
Author: Ishanki Saxena
Author-email: saxenaishanki@gmail.com
